{
    "blenderLocation" : "C:\\Program Files\\Blender Foundation\\Blender\\blender.exe",
    "renderLocation" : "//Output//",
    "scriptLocation" : "G:\\Blender Projects\\blender-icon-generator\\IconGenerator.py",
    "renderFormat" : "JPEG",

    "file" : "G://Blender Projects//blender-icon-generator//ExampleObjects//monkey.obj",
    "camType" : "PERSP",
    "renderSize" : "(1024,1024)",
    "pixBorder" : 10,
    "camRot" : "(60,0,30)",
    "samples" : 10,
    "bgColour" : "(1,1,1,1)",
    "vignette" : 0,

    "logFileLocation" : "G:\\Blender Projects\\blender-icon-generator\\Logs\\log.txt"
}